valk/__init__.py
valk/computer.py
valk/errors.py
valk/integrations/__init__.py
valk/integrations/anthropic.py
valk/static/viewer.html
valk-0.1.0.dist-info/METADATA
valk-0.1.0.dist-info/WHEEL
valk-0.1.0.dist-info/licenses/LICENSE
valk-0.1.0.dist-info/RECORD
